SequenceLibrary/__init__.py
SequenceLibrary/keywords.py
robotframework_sequencelibrary-1.0.1.dist-info/LICENSE
robotframework_sequencelibrary-1.0.1.dist-info/METADATA
robotframework_sequencelibrary-1.0.1.dist-info/WHEEL
robotframework_sequencelibrary-1.0.1.dist-info/top_level.txt
robotframework_sequencelibrary-1.0.1.dist-info/RECORD
