Metadata-Version: 2.1
Name: robotframework-sequencelibrary
Version: 1.0.1
Summary: Robot Framework library for running keywords in sequence.
Author: Mauricio Gutierrez
License: MIT License
Project-URL: Documentation, https://crsdet.github.io/robotframework-sequencelibrary/
Project-URL: Homepage, https://github.com/crsdet/robotframework-sequencelibrary
Keywords: robotframework
Classifier: Framework :: Robot Framework :: Library
Classifier: License :: OSI Approved :: MIT License
Classifier: Programming Language :: Python :: 3.8
Classifier: Programming Language :: Python :: 3.9
Classifier: Programming Language :: Python :: 3.10
Classifier: Programming Language :: Python :: 3.11
Classifier: Topic :: Software Development :: Testing
Requires-Python: >=3.8
License-File: LICENSE
Requires-Dist: robotframework
